node.ext.yaml-0.3-py3.9-nspkg.pth
node/ext/yaml/__init__.py
node/ext/yaml/_yaml.py
node/ext/yaml/behaviors.py
node/ext/yaml/interfaces.py
node/ext/yaml/tests.py
node.ext.yaml-0.3.dist-info/LICENSE.rst
node.ext.yaml-0.3.dist-info/METADATA
node.ext.yaml-0.3.dist-info/WHEEL
node.ext.yaml-0.3.dist-info/namespace_packages.txt
node.ext.yaml-0.3.dist-info/top_level.txt
node.ext.yaml-0.3.dist-info/RECORD
