Metadata-Version: 2.1
Name: node.ext.yaml
Version: 0.3
Summary: Node tree implementation for yaml files
Home-page: https://github.com/conestack/node.ext.yaml
Author: Node Contributors
Author-email: dev@conestack.org
License: Simplified BSD
Keywords: node yaml
Platform: UNKNOWN
Classifier: License :: OSI Approved :: BSD License
Classifier: Intended Audience :: Developers
Classifier: Topic :: Software Development
Classifier: Operating System :: OS Independent
Classifier: Programming Language :: Python
Classifier: Programming Language :: Python :: 2.7
Classifier: Programming Language :: Python :: 3.3
Classifier: Programming Language :: Python :: 3.4
Classifier: Programming Language :: Python :: 3.5
Classifier: Programming Language :: Python :: 3.6
Requires-Dist: node.ext.fs
Requires-Dist: node (>=1.0)
Requires-Dist: pyyaml
Requires-Dist: setuptools
Provides-Extra: test
Requires-Dist: coverage ; extra == 'test'
Requires-Dist: zope.testrunner ; extra == 'test'
